SCNIC/__init__.py
SCNIC/annotate_correls.py
SCNIC/between_correls.py
SCNIC/calculate_permutation_stats.py
SCNIC/calculate_permutations.py
SCNIC/correlation_analysis.py
SCNIC/general.py
SCNIC/module.py
SCNIC/module_analysis.py
SCNIC/within_correls.py
SCNIC-0.6.6.data/scripts/SCNIC_analysis.py
SCNIC-0.6.6.data/scripts/module_enrichment.py
SCNIC-0.6.6.dist-info/LICENSE
SCNIC-0.6.6.dist-info/METADATA
SCNIC-0.6.6.dist-info/WHEEL
SCNIC-0.6.6.dist-info/top_level.txt
SCNIC-0.6.6.dist-info/RECORD
