Metadata-Version: 2.1
Name: SCNIC
Version: 0.6.6
Summary: A tool for finding and summarizing modules of highly correlated observations in compositional data
Home-page: https://github.com/lozuponelab/SCNIC/
Download-URL: https://github.com/lozuponelab/SCNIC/tarball/0.6.6
Author: Lozupone Lab
Author-email: lozuponelab.dev@olucdenver.onmicrosoft.com
License-File: LICENSE
Requires-Dist: numpy
Requires-Dist: scipy <=1.10.1,>=1.9.0
Requires-Dist: networkx >=2
Requires-Dist: biom-format
Requires-Dist: pandas >=1
Requires-Dist: scikit-bio
Requires-Dist: statsmodels
Requires-Dist: tqdm
Requires-Dist: seaborn
Requires-Dist: h5py
